flask_squeeze/__init__.py
flask_squeeze/cache.py
flask_squeeze/compress.py
flask_squeeze/flask_squeeze.py
flask_squeeze/log.py
flask_squeeze/minify.py
flask_squeeze/models.py
flask_squeeze/utils.py
flask_squeeze-3.4.0.dist-info/METADATA
flask_squeeze-3.4.0.dist-info/WHEEL
flask_squeeze-3.4.0.dist-info/top_level.txt
flask_squeeze-3.4.0.dist-info/RECORD
