Metadata-Version: 2.4
Name: flask-squeeze
Version: 3.4.0
Summary: Compress and minify Flask responses!
Author-email: Marcel Kröker <kroeker.marcel@gmail.com>
License: MIT License
Classifier: Programming Language :: Python :: 3
Classifier: License :: OSI Approved :: MIT License
Classifier: Operating System :: OS Independent
Classifier: Intended Audience :: Developers
Classifier: Programming Language :: Python
Classifier: Topic :: Software Development :: Libraries :: Python Modules
Requires-Python: <3.14,>=3.8
Requires-Dist: flask>=1
Requires-Dist: werkzeug>=0
Requires-Dist: brotli~=1.1
Requires-Dist: rjsmin~=1.2
Requires-Dist: rcssmin~=1.2
